theoddevegame.py
theoddevegame-1.1.1.dist-info/METADATA
theoddevegame-1.1.1.dist-info/WHEEL
theoddevegame-1.1.1.dist-info/top_level.txt
theoddevegame-1.1.1.dist-info/RECORD
