Metadata-Version: 2.1
Name: theoddevegame
Version: 1.1.1
Summary: The digitised odd eve game (The hand cricket version). The version 1.1.1 offers fixes some bugs and minor improvements from v1.1: error in SuperOver.
Author: Prashant Bhatt
Author-email: pb3924924@gmail.com
Classifier: Programming Language :: Python :: 3
Classifier: Operating System :: OS Independent
Requires-Python: >=3.6
